graphex_webautomation_plugin/__init__.py
graphex_webautomation_plugin/constants.py
graphex_webautomation_plugin/datatypes.py
graphex_webautomation_plugin/exceptions.py
graphex_webautomation_plugin/actions/__init__.py
graphex_webautomation_plugin/actions/playwright.py
graphex_webautomation_plugin-1.1.2.dist-info/licenses/LICENSE
graphex_webautomation_plugin-1.1.2.dist-info/METADATA
graphex_webautomation_plugin-1.1.2.dist-info/WHEEL
graphex_webautomation_plugin-1.1.2.dist-info/top_level.txt
graphex_webautomation_plugin-1.1.2.dist-info/RECORD
