Metadata-Version: 2.4
Name: graphex-webautomation-plugin
Version: 1.1.2
Summary: A plugin for adding playwright nodes to graphex.
Author: The MITRE Corporation
Requires-Python: >=3.8
License-File: LICENSE
Requires-Dist: mitre-graphex>=1.16.0
Requires-Dist: playwright==1.46.0
Dynamic: author
Dynamic: license-file
Dynamic: requires-dist
Dynamic: requires-python
Dynamic: summary
